{
    "sustainabilityData": [
      { "place": "USA", "year": 2021, "value": 4.5 },
      { "place": "USA", "year": 2022, "value": 5 },
      { "place": "USA", "year": 2023, "value": 5.5 },
      { "place": "USA", "year": 2024, "value": 6 },
      { "place": "Canada", "year": 2021, "value": 6.5 },
      { "place": "Canada", "year": 2022, "value": 13 },
      { "place": "Canada", "year": 2023, "value": 14 },
      { "place": "Canada", "year": 2024, "value": 15 },
      { "place": "United Kingdom", "year": 2021, "value": 1.0 },
      { "place": "United Kingdom", "year": 2022, "value": 4.3 },
      { "place": "United Kingdom", "year": 2023, "value": 4.4 },
      { "place": "United Kingdom", "year": 2024, "value": 4.5 },
      { "place": "Australia", "year": 2021, "value": 7 },
      { "place": "Australia", "year": 2022, "value": 14 },
      { "place": "Australia", "year": 2023, "value": 14.5 },
      { "place": "Australia", "year": 2024, "value": 15 },
      { "place": "New Zealand", "year": 2021, "value": 2.5 },
      { "place": "New Zealand", "year": 2022, "value": 5 },
      { "place": "New Zealand", "year": 2023, "value": 5.8 },
      { "place": "New Zealand", "year": 2024, "value": 6 },
      { "place": "Norway", "year": 2021, "value": 3 },
      { "place": "Norway", "year": 2022, "value": 6 },
      { "place": "Norway", "year": 2023, "value": 7 },
      { "place": "Norway", "year": 2024, "value": 8 },
      { "place": "Taiwan", "year": 2021, "value": 5.2 },
      { "place": "Taiwan", "year": 2022, "value": 11 },
      { "place": "Taiwan", "year": 2023, "value": 11.2 },
      { "place": "Taiwan", "year": 2024, "value": 12 },
      { "place": "Germany", "year": 2021, "value": 3.4 },
      { "place": "Germany", "year": 2022, "value": 7 },
      { "place": "Germany", "year": 2023, "value": 7.1 },
      { "place": "Germany", "year": 2024, "value": 8 }
    ],
    "users": [
      { "id": 1, "name": "John Doe", "email": "john@example.com", "company": { "name": "ABC Corp" } },
      { "id": 2, "name": "Jane Smith", "email": "jane@example.com", "company": { "name": "XYZ Inc" } }
    ]
  }
  